taker/BestTopDownStrategyTaker.py
taker/DualStopLossManager.py
taker/LiquidityGrabStrategyTaker.py
taker/SMCSLAndTPTaker.py
taker/StrategyTaker.py
taker/ThreeLineTradingTaker.py
taker/TrailingSLAndTPTaker.py
taker/TrailingSLTaker.py
taker/__init__.py
taker/history_code/chua_bitget.py
taker/history_code/chua_bn.py
taker/history_code/chua_ok.py
taker/history_code/chua_ok_all.py
taker/history_code/chua_ok_bot.py
taker/history_code/config.py
taker/main.py
openfund_taker-2.5.50.dist-info/METADATA
openfund_taker-2.5.50.dist-info/WHEEL
openfund_taker-2.5.50.dist-info/entry_points.txt
openfund_taker-2.5.50.dist-info/RECORD
